rag_firewall/__init__.py
rag_firewall/audit.py
rag_firewall/cli.py
rag_firewall/firewall.py
rag_firewall/graph/__init__.py
rag_firewall/graph/types.py
rag_firewall/graph/wrapper.py
rag_firewall/integrations/__init__.py
rag_firewall/integrations/langchain.py
rag_firewall/integrations/llamaindex.py
rag_firewall/integrations/graph/__init__.py
rag_firewall/integrations/graph/base.py
rag_firewall/integrations/graph/networkx_adapter.py
rag_firewall/policies/__init__.py
rag_firewall/policies/engine.py
rag_firewall/provenance/__init__.py
rag_firewall/provenance/hasher.py
rag_firewall/provenance/store.py
rag_firewall/scanners/__init__.py
rag_firewall/scanners/conflict_scanner.py
rag_firewall/scanners/encoding_scanner.py
rag_firewall/scanners/pii_scanner.py
rag_firewall/scanners/regex_scanner.py
rag_firewall/scanners/secrets_scanner.py
rag_firewall/scanners/url_scanner.py
rag_firewall/schema/__init__.py
rag_firewall/schema/firewall.schema.json
rag_firewall-0.4.1.dist-info/licenses/LICENSE
rag_firewall-0.4.1.dist-info/licenses/NOTICE
rag_firewall-0.4.1.dist-info/METADATA
rag_firewall-0.4.1.dist-info/WHEEL
rag_firewall-0.4.1.dist-info/entry_points.txt
rag_firewall-0.4.1.dist-info/top_level.txt
rag_firewall-0.4.1.dist-info/RECORD
