Metadata-Version: 2.4
Name: rag-firewall
Version: 0.4.1
Summary: Client-side retrieval firewall for RAG systems — blocks prompt injection and secret leaks, re-ranks stale or untrusted content, and keeps all data inside your environment.
Author: RAG Firewall Maintainers
License: Apache-2.0
Project-URL: Homepage, https://github.com/taladari/rag-firewall
Project-URL: Repository, https://github.com/taladari/rag-firewall
Requires-Python: >=3.9
License-File: LICENSE
License-File: NOTICE
Requires-Dist: pyyaml>=6.0
Requires-Dist: regex>=2023.10.3
Provides-Extra: graph
Requires-Dist: networkx>=3.2; extra == "graph"
Provides-Extra: dev
Requires-Dist: pytest>=7.4; extra == "dev"
Requires-Dist: networkx>=3.2; extra == "dev"
Dynamic: license-file
